clio_api_model_generator/__init__.py
clio_api_model_generator/generators/__init__.py
clio_api_model_generator/generators/clio/manage/__init__.py
clio_api_model_generator/generators/clio/manage/builder.py
clio_api_model_generator/generators/clio/manage/components.py
clio_api_model_generator/generators/clio/manage/config.py
clio_api_model_generator/generators/clio/manage/endpoints.py
clio_api_model_generator/generators/clio/manage/fields.py
clio_api_model_generator/generators/clio/manage/query.py
clio_api_model_generator/generators/clio/manage/request_body.py
clio_api_model_generator/generators/clio/manage/static/__init__.py
clio_api_model_generator/generators/clio/manage/static/models_registry.py
clio_api_model_generator/generators/clio/manage/utils/__init__.py
clio_api_model_generator/generators/clio/manage/utils/sort_schema.py
clio_api_model_generator-0.2.3.dist-info/licenses/LICENSE
clio_api_model_generator-0.2.3.dist-info/METADATA
clio_api_model_generator-0.2.3.dist-info/WHEEL
clio_api_model_generator-0.2.3.dist-info/top_level.txt
clio_api_model_generator-0.2.3.dist-info/RECORD
