Metadata-Version: 2.4
Name: clio_api_model_generator
Version: 0.2.3
Summary: A utility to generate Clio API models from OpenAPI specifications for use with our Clio API Python Client.
Author-email: Unigrated Partners <dev@unigratedpartners.com>
License-Expression: Apache-2.0
Project-URL: Homepage, https://github.com/unigrated-solutions/clio-api-model-generator
Project-URL: Clio API Python Client, https://github.com/unigrated-solutions/clio-api-python-client
Requires-Python: >=3.8
License-File: LICENSE
Requires-Dist: requests
Requires-Dist: PyYAML
Dynamic: license-file
